LICENSE
MANIFEST.in
README.md
setup.py
chaqum/__init__.py
chaqum/__main__.py
chaqum/cmdline.py
chaqum/dataclasses.py
chaqum/flowcontrolmixin.py
chaqum/lib.py
chaqum/logging.console.json
chaqum/logging.syslog.json
chaqum/manager.py
chaqum/util.py
chaqum.egg-info/PKG-INFO
chaqum.egg-info/SOURCES.txt
chaqum.egg-info/dependency_links.txt
chaqum.egg-info/entry_points.txt
chaqum.egg-info/requires.txt
chaqum.egg-info/top_level.txt
chaqum/tasks/__init__.py
chaqum/tasks/command.py
chaqum/tasks/logging.py
chaqum/tasks/stats.py
man/chaqum.1
man/chaqum.lib.3