Metadata-Version: 2.1
Name: chaqum
Version: 0.10
Summary: [ˈkeɪkjuːm], the queue manager for chaotic job queues.
Home-page: https://github.com/wagnerflo/chaqum
Author: Florian Wagner
Author-email: florian@wagner-flo.net
License: UNKNOWN
Platform: UNKNOWN
Classifier: Development Status :: 4 - Beta
Classifier: Environment :: No Input/Output (Daemon)
Classifier: Intended Audience :: Developers
Classifier: Intended Audience :: System Administrators
Classifier: License :: OSI Approved :: Apache Software License
Classifier: Operating System :: POSIX
Classifier: Programming Language :: Python :: 3 :: Only
Requires-Python: >= 3.8
